<?xml version="1.0" encoding="utf-8" ?>
<Updates>
  <Application>
    <Version>33.0.0.6228</Version>
    <URL>https://www.easycoding.org/files/srcrepair_latest.exe</URL>
    <Hash>54ab30936bfd773de11e4e01ac0761b9</Hash>
  </Application>
  <GameDB>
    <Version>master</Version>
    <URL>https://www.easycoding.org/files/srcrepair/updates/games.xml</URL>
    <Hash>ab92aa07cf8573c7ae9abd735a41f7e8</Hash>
  </GameDB>
  <HUDDB>
    <Version>master</Version>
    <URL>https://www.easycoding.org/files/srcrepair/updates/huds.xml</URL>
    <Hash>92bb1d93763d65258fd58d75ad68d7d1</Hash>
  </HUDDB>
  <CfgDB>
    <Version>master</Version>
    <URL>https://www.easycoding.org/files/srcrepair/updates/configs.xml</URL>
    <Hash>65954ddbb2aff6e5e765aa64469b86c8</Hash>
  </CfgDB>
</Updates>
